iomaps/__init__.py
iomaps/_version.py
iomaps/cli.py
iomaps/filter_7z.py
iomaps/helpers.py
iomaps/infer_schema.py
iomaps/pyqt_ui.py
iomaps/streaming.py
iomaps/commands/__init__.py
iomaps/commands/filter_7z.py
iomaps/commands/infer_schema.py
iomaps/commands/schema_common.py
iomaps-0.1.5.dist-info/METADATA
iomaps-0.1.5.dist-info/WHEEL
iomaps-0.1.5.dist-info/entry_points.txt
iomaps-0.1.5.dist-info/RECORD
